physicsworks/__init__.py
physicsworks/greet.py
physicsworks/threejs.py
physicsworks/events/Geometry.py
physicsworks/events/Mesh.py
physicsworks/events/__init__.py
physicsworks/nats/__init__.py
physicsworks/nats/listener.py
physicsworks/nats/publisher.py
physicsworks/solver/__init__.py
physicsworks/solver/config.py
physicsworks/solver/core.py
physicsworks/solver/executor.py
physicsworks/solver/helpers.py
physicsworks/solver/interface.py
physicsworks/solver/logger.py
physicsworks/solver/server.py
physicsworks/solver/utils.py
physicsworks/solver/watcher.py
physicsworks/wrappers/MongoClientWrapper.py
physicsworks/wrappers/NatsClientWrapper.py
physicsworks/wrappers/SocketIOClientWrapper.py
physicsworks/wrappers/SocketIOServerWrapper.py
physicsworks/wrappers/__init__.py
physicsworks-1.0.2.dist-info/METADATA
physicsworks-1.0.2.dist-info/WHEEL
physicsworks-1.0.2.dist-info/top_level.txt
physicsworks-1.0.2.dist-info/RECORD
