Metadata-Version: 2.4
Name: physicsworks
Version: 1.0.2
Summary: PhysicsWorks Python Runner - Simulation execution and post-processing framework
Author: PhysicsWorks
Author-email: contact@physicsworks.io
Classifier: Programming Language :: Python :: 3
Classifier: License :: OSI Approved :: MIT License
Classifier: Operating System :: OS Independent
Requires-Python: >=3.6
Requires-Dist: setuptools
Requires-Dist: packaging
Requires-Dist: GPUtil
Requires-Dist: numpy
Requires-Dist: psutil
Requires-Dist: python-slugify
Requires-Dist: PyYAML
Requires-Dist: requests
Requires-Dist: text-unidecode
Requires-Dist: urllib3
Requires-Dist: watchdog
Requires-Dist: Pillow
Dynamic: author
Dynamic: author-email
Dynamic: classifier
Dynamic: requires-dist
Dynamic: requires-python
Dynamic: summary
